LICENSE
README.md
setup.py
easywork/__init__.py
easywork.egg-info/PKG-INFO
easywork.egg-info/SOURCES.txt
easywork.egg-info/dependency_links.txt
easywork.egg-info/requires.txt
easywork.egg-info/top_level.txt
easywork/api/__init__.py
easywork/api/timezone.py
easywork/auth/__init__.py
easywork/auth/trial.py
easywork/base/__init__.py
easywork/base/cipher.py
easywork/base/config.py
easywork/base/logger.py
easywork/base/thread.py
easywork/ui/__init__.py
easywork/ui/signal/__init__.py
easywork/ui/signal/log_signal.py
easywork/ui/signal/msg_signal.py
easywork/ui/signal/table_signal.py
easywork/ui/widget/__init__.py
easywork/ui/widget/combo_check_box.py
easywork/util/__init__.py
easywork/util/generator.py
easywork/util/native.py
easywork/util/request.py
easywork/util/safe.py
easywork/util/steganography.py
easywork/util/time.py