Metadata-Version: 2.1
Name: easywork
Version: 0.0.28
Summary: 泡面加出品
Home-page: https://www.paomian.plus
Author: paomianplus
Author-email: paomianplus@foxmail.com
License: UNKNOWN
Platform: UNKNOWN
License-File: LICENSE
